{
	"stringList" :
	{
		"import_name" : ["喘ぎ女性ハード"],
		"import_stage1" : [
			"u#ヒイッ……いやああっ",
			"u#やめて！……いやあああっ！",
			"u#アアッ、んぐっ、ヒイイイッ！",
			"u#やだ……やだ……",
			"u#ひいいい……ッ",
			"#ssend"
			],
		"import_stage2" : [
			"u#ひぐっ……ひぎいっ……アアアッ！",
			"u#壊れる……壊れちゃう……ッ！",
			"u#ひいっ、ハッ、ハッ、アアッ！",
			"u#ダメええええっ……ッ！",
			"u#あはあっ、ひっ、あぎいっ！",
			"u#んくうっ、ううっ、ひうううっ",
			"u#…誰か……助けて……",
			"#ssend"
			],
		"import_stage3" : [
			"u#いや……ひっ、いやああっ",
			"u#アッ、ハッ、ハッ……アアッ",
			"u#ダメッ……そこは……アアアアッ",
			"u#ヒイイッ、ぎやああああっ",
			"u#あっ、あっ、もうイヤ…　もうダメ…",
			"u#お願い…　ゆるして…",
			"#ssend"
			],
		"import_stage4" : [
			"u#アアッ、ヒッ…ヒッ…ヒッ…ヒャアアッ",
			"u#ヒッ、死んじゃう、アアッ、あひいっ、ひいっ",
			"u#んくっ、おはあっ、がはっ、がっ",
			"u#げはっ、アッ、ううっ",
			"u#アアアアーッ、ダメーッ、ダメーッ、ヒイイイッ",
			"u#いやあああ、ぎゃあああ、助けてええ！！",
			"u#やめっ……やめて……アアアアッ！",
			"u#死ぬ……イヤ……いひゃああっ、ヒイイッ",
			"#ssend"
			],
		"import_stage5" : [
			"u#アアアアッ……アアッ……アアッ……",
			"u#…ハア……んごふっ……ハア……",
			"u#……はあ……はあ……",
			"#ssend"
			]
	}
}
